{"errors":[],"warnings":[],"namedChunkGroups":{"polyfill":{"chunks":[2,0,8],"assets":["webpack-runtime-4ec0261125b0f79030ca.js","webpack-runtime-4ec0261125b0f79030ca.js.map","commons-c7398053d953df423582.js","commons-c7398053d953df423582.js.map","polyfill-96c0e71935cde5505b8a.js","polyfill-96c0e71935cde5505b8a.js.map"],"children":{},"childAssets":{}},"app":{"chunks":[2,7,4],"assets":["webpack-runtime-4ec0261125b0f79030ca.js","webpack-runtime-4ec0261125b0f79030ca.js.map","framework-ec9802df7dfd0ab94355.js","framework-ec9802df7dfd0ab94355.js.map","app-13be710f08c5e3d6d015.js","app-13be710f08c5e3d6d015.js.map"],"children":{},"childAssets":{}},"component---src-pages-404-tsx":{"chunks":[1,0,5],"assets":["styles.807f6e4a6c88e63d8e81.css","styles-e9d24b1846c7d6eb9685.js","styles-e9d24b1846c7d6eb9685.js.map","commons-c7398053d953df423582.js","commons-c7398053d953df423582.js.map","component---src-pages-404-tsx-379b050502bfa9574aef.js","component---src-pages-404-tsx-379b050502bfa9574aef.js.map"],"children":{},"childAssets":{}},"component---src-pages-index-tsx":{"chunks":[1,3,0,6],"assets":["styles.807f6e4a6c88e63d8e81.css","styles-e9d24b1846c7d6eb9685.js","styles-e9d24b1846c7d6eb9685.js.map","95b64a6e-06ef4bd1020fada1bca7.js","95b64a6e-06ef4bd1020fada1bca7.js.map","commons-c7398053d953df423582.js","commons-c7398053d953df423582.js.map","component---src-pages-index-tsx-3e2d0919cbd9bd652c47.js","component---src-pages-index-tsx-3e2d0919cbd9bd652c47.js.map"],"children":{},"childAssets":{}}},"assetsByChunkName":{"polyfill":["webpack-runtime-4ec0261125b0f79030ca.js","commons-c7398053d953df423582.js","polyfill-96c0e71935cde5505b8a.js"],"app":["webpack-runtime-4ec0261125b0f79030ca.js","framework-ec9802df7dfd0ab94355.js","app-13be710f08c5e3d6d015.js"],"component---src-pages-404-tsx":["styles.807f6e4a6c88e63d8e81.css","styles-e9d24b1846c7d6eb9685.js","commons-c7398053d953df423582.js","component---src-pages-404-tsx-379b050502bfa9574aef.js"],"component---src-pages-index-tsx":["styles.807f6e4a6c88e63d8e81.css","styles-e9d24b1846c7d6eb9685.js","95b64a6e-06ef4bd1020fada1bca7.js","commons-c7398053d953df423582.js","component---src-pages-index-tsx-3e2d0919cbd9bd652c47.js"]}}